audiotext/__init__.py
audiotext/audio2text.py
AudioText-0.0.4.dist-info/METADATA
AudioText-0.0.4.dist-info/WHEEL
AudioText-0.0.4.dist-info/top_level.txt
AudioText-0.0.4.dist-info/RECORD
