Metadata-Version: 2.1
Name: AudioText
Version: 0.0.4
Summary: Convert Arabic Audio To English Text Module 
Home-page: https://github.com/falahgs/
Author: Falahgs.G.Saleih
Author-email: falahgs07@gmail.com
License: MIT
Keywords: Audio,Audio2text
Classifier: Programming Language :: Python :: 3
Classifier: License :: OSI Approved :: MIT License
Classifier: Operating System :: OS Independent
Requires-Python: >=3.6
Requires-Dist: gtts
Requires-Dist: speechrecognition
Requires-Dist: playsound
Requires-Dist: pydub
Requires-Dist: googletrans (==3.1.0a0)
